nsopen/__init__.py
nsopen/__main__.py
nsopen/cli.py
nsopen/nsopen.py
nsopen-0.1.0.dist-info/licenses/LICENSE
nsopen-0.1.0.dist-info/METADATA
nsopen-0.1.0.dist-info/WHEEL
nsopen-0.1.0.dist-info/entry_points.txt
nsopen-0.1.0.dist-info/top_level.txt
nsopen-0.1.0.dist-info/RECORD
