Metadata-Version: 2.4
Name: nsopen
Version: 0.1.0
Summary: A tool to perform DNS lookup and open IP addresses in a browser
Author: Nelson Chan
License: MIT License
Project-URL: Repository, https://github.com/khchanel/nsopen.git
Classifier: Programming Language :: Python :: 3
Classifier: Operating System :: OS Independent
Requires-Python: >=3.8
License-File: LICENSE
Provides-Extra: dev
Requires-Dist: pytest; extra == "dev"
Dynamic: license-file
